cnbdber/__init__.py
cnbdber/__main__.py
cnbdber/cli.py
cnbdber/config.py
cnbdber/core.py
cnbdber/logger.py
cnbdber-0.3.1.dist-info/licenses/LICENSE
cnbdber-0.3.1.dist-info/METADATA
cnbdber-0.3.1.dist-info/WHEEL
cnbdber-0.3.1.dist-info/entry_points.txt
cnbdber-0.3.1.dist-info/top_level.txt
cnbdber-0.3.1.dist-info/RECORD
