Metadata-Version: 2.4
Name: cnbdber
Version: 0.3.1
Summary: CNBDBer: Universal DB runner for SQL-like commands across SQLite/MySQL/PostgreSQL/MongoDB
Author-email: "Mr. Clark" <geoff@cnb.llc>
License-Expression: MIT
Project-URL: Homepage, https://github.com/AznIronMan/cnbdber
Project-URL: Repository, https://github.com/AznIronMan/cnbdber.git
Keywords: database,cli,sql,sqlite,mysql,postgresql,mongodb
Classifier: Programming Language :: Python :: 3
Classifier: Programming Language :: Python :: 3.9
Classifier: Programming Language :: Python :: 3.10
Classifier: Programming Language :: Python :: 3.11
Classifier: Programming Language :: Python :: 3.12
Classifier: Environment :: Console
Classifier: Intended Audience :: Developers
Classifier: Topic :: Database
Classifier: Topic :: Utilities
Requires-Python: >=3.9
License-File: LICENSE
Requires-Dist: cnblogger>=0.1.0
Requires-Dist: typing-extensions>=4.6.0; python_version < "3.11"
Provides-Extra: mysql
Requires-Dist: PyMySQL>=1.1.1; extra == "mysql"
Provides-Extra: postgres
Requires-Dist: psycopg2-binary>=2.9.9; extra == "postgres"
Provides-Extra: mongo
Requires-Dist: pymongo>=4.6.0; extra == "mongo"
Provides-Extra: ssh
Requires-Dist: sshtunnel>=0.4.0; extra == "ssh"
Dynamic: license-file
